{
"boxscore": {
"teams": [
{
"team": {
"id": "294",
"uid": "s:40~l:54~t:294",
"slug": "jacksonville-dolphins",
"location": "Jacksonville",
"name": "Dolphins",
"abbreviation": "JAX",
"displayName": "Jacksonville Dolphins",
"shortDisplayName": "Jacksonville",
"color": "00523e",
"logo": "https://a.espncdn.com/i/teamlogos/ncaa/500/294.png"
},
"statistics": [
{
"name": "fieldGoalsMade-fieldGoalsAttempted",
"displayValue": "23-60",
"label": "FG"
},
{
"name": "fieldGoalPct",
"displayValue": "38.3",
"abbreviation": "FG%",
"label": "Field Goal %"
},
{
"name": "threePointFieldGoalsMade-threePointFieldGoalsAttempted",
"displayValue": "5-15",
"label": "3PT"
},
{
"name": "threePointFieldGoalPct",
"displayValue": "33.3",
"abbreviation": "3P%",
"label": "Three Point %"
},
{
"name": "freeThrowsMade-freeThrowsAttempted",
"displayValue": "12-22",
"label": "FT"
},
{
"name": "freeThrowPct",
"displayValue": "54.5",
"abbreviation": "FT%",
"label": "Free Throw %"
},
{
"name": "totalRebounds",
"displayValue": "33",
"abbreviation": "REB",
"label": "Rebounds"
},
{
"name": "offensiveRebounds",
"displayValue": "12",
"abbreviation": "OR",
"label": "Offensive Rebounds"
},
{
"name": "defensiveRebounds",
"displayValue": "21",
"abbreviation": "DR",
"label": "Defensive Rebounds"
},
{
"name": "assists",
"displayValue": "10",
"abbreviation": "AST",
"label": "Assists"
},
{
"name": "steals",
"displayValue": "8",
"abbreviation": "STL",
"label": "Steals"
},
{
"name": "blocks",
"displayValue": "2",
"abbreviation": "BLK",
"label": "Blocks"
},
{
"name": "turnovers",
"displayValue": "13",
"abbreviation": "TO",
"label": "Turnovers"
},
{
"name": "teamTurnovers",
"displayValue": "0",
"abbreviation": "TTO",
"label": "Team Turnovers"
},
{
"name": "totalTurnovers",
"displayValue": "13",
"abbreviation": "ToTO",
"label": "Total Turnovers"
},
{
"name": "technicalFouls",
"displayValue": "0",
"abbreviation": "TECH",
"label": "Technical Fouls"
},
{
"name": "totalTechnicalFouls",
"displayValue": "0",
"abbreviation": "TECH",
"label": "Total Technical Fouls"
},
{
"name": "turnoverPoints",
"displayValue": "21",
"abbreviation": "PTS OFF TO",
"label": "Points Off Turnovers"
},
{
"name": "fastBreakPoints",
"displayValue": "9",
"abbreviation": "FBPs",
"label": "Fast Break Points"
},
{
"name": "pointsInPaint",
"displayValue": "26",
"abbreviation": "PIP",
"label": "Points in Paint"
},
{
"name": "fouls",
"displayValue": "15",
"abbreviation": "PF",
"label": "Fouls"
},
{
"name": "largestLead",
"displayValue": "0",
"abbreviation": "LL",
"label": "Largest Lead"
}
],
"displayOrder": 1,
"homeAway": "away"
},
{
"team": {
"id": "2110",
"uid": "s:40~l:54~t:2110",
"slug": "central-arkansas-sugar-bears",
"location": "Central Arkansas",
"name": "Sugar Bears",
"abbreviation": "CARK",
"displayName": "Central Arkansas Sugar Bears",
"shortDisplayName": "C Arkansas",
"color": "a7a9ac",
"alternateColor": "8e959a",
"logo": "https://a.espncdn.com/i/teamlogos/ncaa/500/2110.png"
},
"statistics": [
{
"name": "fieldGoalsMade-fieldGoalsAttempted",
"displayValue": "30-57",
"label": "FG"
},
{
"name": "fieldGoalPct",
"displayValue": "52.6",
"abbreviation": "FG%",
"label": "Field Goal %"
},
{
"name": "threePointFieldGoalsMade-threePointFieldGoalsAttempted",
"displayValue": "8-21",
"label": "3PT"
},
{
"name": "threePointFieldGoalPct",
"displayValue": "38.1",
"abbreviation": "3P%",
"label": "Three Point %"
},
{
"name": "freeThrowsMade-freeThrowsAttempted",
"displayValue": "6-9",
"label": "FT"
},
{
"name": "freeThrowPct",
"displayValue": "66.7",
"abbreviation": "FT%",
"label": "Free Throw %"
},
{
"name": "totalRebounds",
"displayValue": "40",
"abbreviation": "REB",
"label": "Rebounds"
},
{
"name": "offensiveRebounds",
"displayValue": "9",
"abbreviation": "OR",
"label": "Offensive Rebounds"
},
{
"name": "defensiveRebounds",
"displayValue": "31",
"abbreviation": "DR",
"label": "Defensive Rebounds"
},
{
"name": "assists",
"displayValue": "18",
"abbreviation": "AST",
"label": "Assists"
},
{
"name": "steals",
"displayValue": "11",
"abbreviation": "STL",
"label": "Steals"
},
{
"name": "blocks",
"displayValue": "10",
"abbreviation": "BLK",
"label": "Blocks"
},
{
"name": "turnovers",
"displayValue": "17",
"abbreviation": "TO",
"label": "Turnovers"
},
{
"name": "teamTurnovers",
"displayValue": "1",
"abbreviation": "TTO",
"label": "Team Turnovers"
},
{
"name": "totalTurnovers",
"displayValue": "17",
"abbreviation": "ToTO",
"label": "Total Turnovers"
},
{
"name": "technicalFouls",
"displayValue": "0",
"abbreviation": "TECH",
"label": "Technical Fouls"
},
{
"name": "totalTechnicalFouls",
"displayValue": "0",
"abbreviation": "TECH",
"label": "Total Technical Fouls"
},
{
"name": "turnoverPoints",
"displayValue": "19",
"abbreviation": "PTS OFF TO",
"label": "Points Off Turnovers"
},
{
"name": "fastBreakPoints",
"displayValue": "4",
"abbreviation": "FBPs",
"label": "Fast Break Points"
},
{
"name": "pointsInPaint",
"displayValue": "38",
"abbreviation": "PIP",
"label": "Points in Paint"
},
{
"name": "fouls",
"displayValue": "20",
"abbreviation": "PF",
"label": "Fouls"
},
{
"name": "largestLead",
"displayValue": "21",
"abbreviation": "LL",
"label": "Largest Lead"
}
],
"displayOrder": 2,
"homeAway": "home"
}
],
"players": [
{
"team": {
"id": "294",
"uid": "s:40~l:54~t:294",
"slug": "jacksonville-dolphins",
"location": "Jacksonville",
"name": "Dolphins",
"abbreviation": "JAX",
"displayName": "Jacksonville Dolphins",
"shortDisplayName": "Jacksonville",
"color": "00523e",
"logo": "https://a.espncdn.com/i/teamlogos/ncaa/500/294.png"
},
"statistics": [
{
"names": [
"MIN",
"FG",
"3PT",
"FT",
"OREB",
"DREB",
"REB",
"AST",
"STL",
"BLK",
"TO",
"PF",
"PTS"
],
"keys": [
"minutes",
"fieldGoalsMade-fieldGoalsAttempted",
"threePointFieldGoalsMade-threePointFieldGoalsAttempted",
"freeThrowsMade-freeThrowsAttempted",
"offensiveRebounds",
"defensiveRebounds",
"rebounds",
"assists",
"steals",
"blocks",
"turnovers",
"fouls",
"points"
],
"labels": [
"MIN",
"FG",
"3PT",
"FT",
"OREB",
"DREB",
"REB",
"AST",
"STL",
"BLK",
"TO",
"PF",
"PTS"
],
"descriptions": [
"Minutes",
"Field Goals Made/Attempted",
"3-Point Field Goals Made/Attempted",
"Free Throws Made/Attempted",
"Offensive Rebounds",
"Defensive Rebounds",
"Rebounds",
"Assists",
"Steals",
"Blocks",
"Turnovers",
"Personal Fouls",
"Points"
],
"athletes": [
{
"active": false,
"athlete": {
"id": "5175447",
"uid": "s:40~l:54~a:5175447",
"guid": "1d1475b9-2478-3610-b6d9-135abb1535eb",
"displayName": "Saniyah Craig",
"shortName": "S. Craig",
"links": [
{
"rel": [
"playercard",
"desktop",
"athlete"
],
"href": "https://www.espn.com/womens-college-basketball/player/_/id/5175447/saniyah-craig",
"text": "Player Card"
}
],
"headshot": {
"href": "https://a.espncdn.com/i/headshots/womens-college-basketball/players/full/5175447.png",
"alt": "Saniyah Craig"
},
"jersey": "15",
"position": {
"name": "Forward",
"displayName": "Forward",
"abbreviation": "F"
}
},
"starter": true,
"didNotPlay": false,
"ejected": false,
"stats": [
"30",
"2-8",
"0-2",
"2-3",
"6",
"9",
"15",
"2",
"1",
"0",
"1",
"4",
"6"
]
},
{
"active": false,
"athlete": {
"id": "4595196",
"uid": "s:40~l:54~a:4595196",
"guid": "96880aa3-b13e-3238-b572-e49cb796ceb1",
"displayName": "Makayla Edwards",
"shortName": "M. Edwards",
"links": [
{
"rel": [
"playercard",
"desktop",
"athlete"
],
"href": "https://www.espn.com/womens-college-basketball/player/_/id/4595196/makayla-edwards",
"text": "Player Card"
}
],
"headshot": {
"href": "https://a.espncdn.com/i/headshots/womens-college-basketball/players/full/4595196.png",
"alt": "Makayla Edwards"
},
"jersey": "4",
"position": {
"name": "Forward",
"displayName": "Forward",
"abbreviation": "F"
}
},
"starter": true,
"didNotPlay": false,
"ejected": false,
"stats": [
"33",
"7-17",
"2-4",
"2-6",
"0",
"1",
"1",
"1",
"0",
"0",
"1",
"2",
"18"
]
},
{
"active": false,
"athlete": {
"id": "5241926",
"uid": "s:40~l:54~a:5241926",
"guid": "5d5ceb3e-47ca-380c-93e7-9faae7d70887",
"displayName": "Comari Mitchell",
"shortName": "C. Mitchell",
"links": [
{
"rel": [
"playercard",
"desktop",
"athlete"
],
"href": "https://www.espn.com/womens-college-basketball/player/_/id/5241926/comari-mitchell",
"text": "Player Card"
}
],
"headshot": {
"href": "https://a.espncdn.com/i/headshots/womens-college-basketball/players/full/5241926.png",
"alt": "Comari Mitchell"
},
"jersey": "5",
"position": {
"name": "Guard",
"displayName": "Guard",
"abbreviation": "G"
}
},
"starter": true,
"didNotPlay": false,
"ejected": false,
"stats": [
"22",
"1-6",
"0-2",
"0-0",
"1",
"0",
"1",
"1",
"1",
"0",
"1",
"2",
"2"
]
},
{
"active": false,
"athlete": {
"id": "5175445",
"uid": "s:40~l:54~a:5175445",
"guid": "a32d981d-d3a2-36eb-9ec7-2b1e2ff5c0c8",
"displayName": "Sana'a Garrett",
"shortName": "S. Garrett",
"links": [
{
"rel": [
"playercard",
"desktop",
"athlete"
],
"href": "https://www.espn.com/womens-college-basketball/player/_/id/5175445/sanaa-garrett",
"text": "Player Card"
}
],
"headshot": {
"href": "https://a.espncdn.com/i/headshots/womens-college-basketball/players/full/5175445.png",
"alt": "Sana'a Garrett"
},
"jersey": "3",
"position": {
"name": "Guard",
"displayName": "Guard",
"abbreviation": "G"
}
},
"starter": true,
"didNotPlay": false,
"ejected": false,
"stats": [
"34",
"4-6",
"0-0",
"2-5",
"1",
"2",
"3",
"1",
"5",
"0",
"2",
"2",
"10"
]
},
{
"active": false,
"athlete": {
"id": "4433734",
"uid": "s:40~l:54~a:4433734",
"guid": "919144bb-6502-3aad-8c89-f84b208fec04",
"displayName": "Priscilla Williams",
"shortName": "P. Williams",
"links": [
{
"rel": [
"playercard",
"desktop",
"athlete"
],
"href": "https://www.espn.com/womens-college-basketball/player/_/id/4433734/priscilla-williams",
"text": "Player Card"
}
],
"headshot": {
"href": "https://a.espncdn.com/i/headshots/womens-college-basketball/players/full/4433734.png",
"alt": "Priscilla Williams"
},
"jersey": "23",
"position": {
"name": "Guard",
"displayName": "Guard",
"abbreviation": "G"
}
},
"starter": true,
"didNotPlay": false,
"ejected": false,
"stats": [
"33",
"6-13",
"2-4",
"2-2",
"1",
"4",
"5",
"3",
"0",
"1",
"5",
"2",
"16"
]
},
{
"active": false,
"athlete": {
"id": "5241927",
"uid": "s:40~l:54~a:5241927",
"guid": "abe5e023-8c93-35ae-8bac-fb4e11850e70",
"displayName": "Mariah Knight",
"shortName": "M. Knight",
"links": [
{
"rel": [
"playercard",
"desktop",
"athlete"
],
"href": "https://www.espn.com/womens-college-basketball/player/_/id/5241927/mariah-knight",
"text": "Player Card"
}
],
"headshot": {
"href": "https://a.espncdn.com/i/headshots/womens-college-basketball/players/full/5241927.png",
"alt": "Mariah Knight"
},
"jersey": "22",
"position": {
"name": "Forward",
"displayName": "Forward",
"abbreviation": "F"
}
},
"starter": false,
"didNotPlay": false,
"ejected": false,
"stats": [
"4",
"0-0",
"0-0",
"0-0",
"0",
"1",
"1",
"1",
"0",
"1",
"0",
"0",
"0"
]
},
{
"active": false,
"athlete": {
"id": "5175450",
"uid": "s:40~l:54~a:5175450",
"guid": "ccd0f3be-bd53-3365-a85c-fcb3ae78cc05",
"displayName": "Jada Jones",
"shortName": "J. Jones",
"links": [
{
"rel": [
"playercard",
"desktop",
"athlete"
],
"href": "https://www.espn.com/womens-college-basketball/player/_/id/5175450/jada-jones",
"text": "Player Card"
}
],
"headshot": {
"href": "https://a.espncdn.com/i/headshots/womens-college-basketball/players/full/5175450.png",
"alt": "Jada Jones"
},
"jersey": "24",
"position": {
"name": "Center",
"displayName": "Center",
"abbreviation": "C"
}
},
"starter": false,
"didNotPlay": false,
"ejected": false,
"stats": [
"11",
"2-4",
"0-0",
"1-2",
"0",
"1",
"1",
"0",
"0",
"0",
"0",
"1",
"5"
]
},
{
"active": false,
"athlete": {
"id": "5241925",
"uid": "s:40~l:54~a:5241925",
"guid": "73eaa98d-ea95-3dbd-baa9-1ef49fc30da6",
"displayName": "Bailey Burns",
"shortName": "B. Burns",
"links": [
{
"rel": [
"playercard",
"desktop",
"athlete"
],
"href": "https://www.espn.com/womens-college-basketball/player/_/id/5241925/bailey-burns",
"text": "Player Card"
}
],
"headshot": {
"href": "https://a.espncdn.com/i/headshots/womens-college-basketball/players/full/5241925.png",
"alt": "Bailey Burns"
},
"jersey": "2",
"position": {
"name": "Guard",
"displayName": "Guard",
"abbreviation": "G"
}
},
"starter": false,
"didNotPlay": false,
"ejected": false,
"stats": [
"16",
"1-5",
"1-2",
"3-4",
"0",
"2",
"2",
"1",
"0",
"0",
"2",
"1",
"6"
]
},
{
"active": false,
"athlete": {
"id": "5175444",
"uid": "s:40~l:54~a:5175444",
"guid": "43020b38-84d4-3b2e-b283-c8c174b81c45",
"displayName": "Isamery Telleria",
"shortName": "I. Telleria",
"links": [
{
"rel": [
"playercard",
"desktop",
"athlete"
],
"href": "https://www.espn.com/womens-college-basketball/player/_/id/5175444/isamery-telleria",
"text": "Player Card"
}
],
"headshot": {
"href": "https://a.espncdn.com/i/headshots/womens-college-basketball/players/full/5175444.png",
"alt": "Isamery Telleria"
},
"jersey": "1",
"position": {
"name": "Guard",
"displayName": "Guard",
"abbreviation": "G"
}
},
"starter": false,
"didNotPlay": false,
"ejected": false,
"stats": [
"13",
"0-1",
"0-1",
"0-0",
"0",
"0",
"0",
"0",
"0",
"0",
"0",
"1",
"0"
]
},
{
"active": false,
"athlete": {
"id": "5107416",
"uid": "s:40~l:54~a:5107416",
"guid": "d03396d0-815e-31c5-b6e5-4f7fc3ab4798",
"displayName": "Julene Royale",
"shortName": "J. Royale",
"links": [
{
"rel": [
"playercard",
"desktop",
"athlete"
],
"href": "https://www.espn.com/womens-college-basketball/player/_/id/5107416/julene-royale",
"text": "Player Card"
}
],
"headshot": {
"href": "https://a.espncdn.com/i/headshots/womens-college-basketball/players/full/5107416.png",
"alt": "Julene Royale"
},
"jersey": "12",
"position": {
"name": "Guard",
"displayName": "Guard",
"abbreviation": "G"
}
},
"starter": false,
"didNotPlay": false,
"ejected": false,
"stats": [
"4",
"0-0",
"0-0",
"0-0",
"0",
"0",
"0",
"0",
"1",
"0",
"1",
"0",
"0"
]
},
{
"active": false,
"athlete": {
"id": "5107418",
"uid": "s:40~l:54~a:5107418",
"guid": "2a61495a-5e73-3688-b55e-9bd9e8c365aa",
"displayName": "Zaria Blake",
"shortName": "Z. Blake",
"links": [
{
"rel": [
"playercard",
"desktop",
"athlete"
],
"href": "https://www.espn.com/womens-college-basketball/player/_/id/5107418/zaria-blake",
"text": "Player Card"
}
],
"headshot": {
"href": "https://a.espncdn.com/i/headshots/womens-college-basketball/players/full/5107418.png",
"alt": "Zaria Blake"
},
"jersey": "11",
"position": {
"name": "Forward",
"displayName": "Forward",
"abbreviation": "F"
}
},
"starter": false,
"didNotPlay": true,
"ejected": false,
"stats": []
},
{
"active": false,
"athlete": {
"id": "4705365",
"uid": "s:40~l:54~a:4705365",
"guid": "1ee46242-819d-3d5f-b26a-abec3046abe3",
"displayName": "Jada Duckett",
"shortName": "J. Duckett",
"links": [
{
"rel": [
"playercard",
"desktop",
"athlete"
],
"href": "https://www.espn.com/womens-college-basketball/player/_/id/4705365/jada-duckett",
"text": "Player Card"
}
],
"headshot": {
"href": "https://a.espncdn.com/i/headshots/womens-college-basketball/players/full/4705365.png",
"alt": "Jada Duckett"
},
"jersey": "20",
"position": {
"name": "Center",
"displayName": "Center",
"abbreviation": "C"
}
},
"starter": false,
"didNotPlay": true,
"ejected": false,
"stats": []
},
{
"active": false,
"athlete": {
"id": "5241928",
"uid": "s:40~l:54~a:5241928",
"guid": "4b8c9216-6824-3d01-89d8-7e4dae6c1294",
"displayName": "Giana Provenzano",
"shortName": "G. Provenzano",
"links": [
{
"rel": [
"playercard",
"desktop",
"athlete"
],
"href": "https://www.espn.com/womens-college-basketball/player/_/id/5241928/giana-provenzano",
"text": "Player Card"
}
],
"headshot": {
"href": "https://a.espncdn.com/i/headshots/womens-college-basketball/players/full/5241928.png",
"alt": "Giana Provenzano"
},
"jersey": "32",
"position": {
"name": "Guard",
"displayName": "Guard",
"abbreviation": "G"
}
},
"starter": false,
"didNotPlay": true,
"ejected": false,
"stats": []
},
{
"active": false,
"athlete": {
"id": "5175449",
"uid": "s:40~l:54~a:5175449",
"guid": "91acd9be-f29f-38e6-b861-6cf74d45614e",
"displayName": "LaRonda Quattlebaum",
"shortName": "L. Quattlebaum",
"links": [
{
"rel": [
"playercard",
"desktop",
"athlete"
],
"href": "https://www.espn.com/womens-college-basketball/player/_/id/5175449/laronda-quattlebaum",
"text": "Player Card"
}
],
"headshot": {
"href": "https://a.espncdn.com/i/headshots/womens-college-basketball/players/full/5175449.png",
"alt": "LaRonda Quattlebaum"
},
"jersey": "13",
"position": {
"name": "Guard",
"displayName": "Guard",
"abbreviation": "G"
}
},
"starter": false,
"didNotPlay": true,
"ejected": false,
"stats": []
},
{
"active": false,
"athlete": {
"id": "4705362",
"uid": "s:40~l:54~a:4705362",
"guid": "56074e33-6b60-3903-bdd3-be6f89cdbe12",
"displayName": "Edyn Battle",
"shortName": "E. Battle",
"links": [
{
"rel": [
"playercard",
"desktop",
"athlete"
],
"href": "https://www.espn.com/womens-college-basketball/player/_/id/4705362/edyn-battle",
"text": "Player Card"
}
],
"headshot": {
"href": "https://a.espncdn.com/i/headshots/womens-college-basketball/players/full/4705362.png",
"alt": "Edyn Battle"
},
"jersey": "10",
"position": {
"name": "Guard",
"displayName": "Guard",
"abbreviation": "G"
}
},
"starter": false,
"didNotPlay": true,
"ejected": false,
"stats": []
}
],
"totals": [
"",
"23-60",
"5-15",
"12-22",
"12",
"21",
"33",
"10",
"8",
"2",
"13",
"15",
"63"
]
}
],
"displayOrder": 1
},
{
"team": {
"id": "2110",
"uid": "s:40~l:54~t:2110",
"slug": "central-arkansas-sugar-bears",
"location": "Central Arkansas",
"name": "Sugar Bears",
"abbreviation": "CARK",
"displayName": "Central Arkansas Sugar Bears",
"shortDisplayName": "C Arkansas",
"color": "a7a9ac",
"alternateColor": "8e959a",
"logo": "https://a.espncdn.com/i/teamlogos/ncaa/500/2110.png"
},
"statistics": [
{
"names": [
"MIN",
"FG",
"3PT",
"FT",
"OREB",
"DREB",
"REB",
"AST",
"STL",
"BLK",
"TO",
"PF",
"PTS"
],
"keys": [
"minutes",
"fieldGoalsMade-fieldGoalsAttempted",
"threePointFieldGoalsMade-threePointFieldGoalsAttempted",
"freeThrowsMade-freeThrowsAttempted",
"offensiveRebounds",
"defensiveRebounds",
"rebounds",
"assists",
"steals",
"blocks",
"turnovers",
"fouls",
"points"
],
"labels": [
"MIN",
"FG",
"3PT",
"FT",
"OREB",
"DREB",
"REB",
"AST",
"STL",
"BLK",
"TO",
"PF",
"PTS"
],
"descriptions": [
"Minutes",
"Field Goals Made/Attempted",
"3-Point Field Goals Made/Attempted",
"Free Throws Made/Attempted",
"Offensive Rebounds",
"Defensive Rebounds",
"Rebounds",
"Assists",
"Steals",
"Blocks",
"Turnovers",
"Personal Fouls",
"Points"
],
"athletes": [
{
"active": false,
"athlete": {
"id": "5175437",
"uid": "s:40~l:54~a:5175437",
"guid": "24d425e8-0e16-3213-a60a-3aeff40b0a8d",
"displayName": "Elizabeth Abiara",
"shortName": "E. Abiara",
"links": [
{
"rel": [
"playercard",
"desktop",
"athlete"
],
"href": "https://www.espn.com/womens-college-basketball/player/_/id/5175437/elizabeth-abiara",
"text": "Player Card"
}
],
"headshot": {
"href": "https://a.espncdn.com/i/headshots/womens-college-basketball/players/full/5175437.png",
"alt": "Elizabeth Abiara"
},
"jersey": "32",
"position": {
"name": "Forward",
"displayName": "Forward",
"abbreviation": "F"
}
},
"starter": true,
"didNotPlay": false,
"ejected": false,
"stats": [
"21",
"5-5",
"0-0",
"0-0",
"1",
"5",
"6",
"2",
"1",
"1",
"1",
"4",
"10"
]
},
{
"active": false,
"athlete": {
"id": "5175433",
"uid": "s:40~l:54~a:5175433",
"guid": "22526e48-d7ee-3f04-bc28-d32c9963efdf",
"displayName": "Bree Stephens",
"shortName": "B. Stephens",
"links": [
{
"rel": [
"playercard",
"desktop",
"athlete"
],
"href": "https://www.espn.com/womens-college-basketball/player/_/id/5175433/bree-stephens",
"text": "Player Card"
}
],
"headshot": {
"href": "https://a.espncdn.com/i/headshots/womens-college-basketball/players/full/5175433.png",
"alt": "Bree Stephens"
},
"jersey": "5",
"position": {
"name": "Forward",
"displayName": "Forward",
"abbreviation": "F"
}
},
"starter": true,
"didNotPlay": false,
"ejected": false,
"stats": [
"30",
"2-5",
"0-2",
"0-0",
"2",
"7",
"9",
"4",
"1",
"6",
"2",
"2",
"4"
]
},
{
"active": false,
"athlete": {
"id": "5175434",
"uid": "s:40~l:54~a:5175434",
"guid": "572f1109-ff06-37c1-8d3f-03de808e79a9",
"displayName": "Leah Mafua",
"shortName": "L. Mafua",
"links": [
{
"rel": [
"playercard",
"desktop",
"athlete"
],
"href": "https://www.espn.com/womens-college-basketball/player/_/id/5175434/leah-mafua",
"text": "Player Card"
}
],
"headshot": {
"href": "https://a.espncdn.com/i/headshots/womens-college-basketball/players/full/5175434.png",
"alt": "Leah Mafua"
},
"jersey": "22",
"position": {
"name": "Guard",
"displayName": "Guard",
"abbreviation": "G"
}
},
"starter": true,
"didNotPlay": false,
"ejected": false,
"stats": [
"27",
"6-9",
"3-4",
"0-0",
"2",
"5",
"7",
"2",
"2",
"1",
"4",
"2",
"15"
]
},
{
"active": false,
"athlete": {
"id": "4900400",
"uid": "s:40~l:54~a:4900400",
"guid": "17080fa9-8b7b-3093-ba4d-c611ac714137",
"displayName": "Kinley Fisher",
"shortName": "K. Fisher",
"links": [
{
"rel": [
"playercard",
"desktop",
"athlete"
],
"href": "https://www.espn.com/womens-college-basketball/player/_/id/4900400/kinley-fisher",
"text": "Player Card"
}
],
"headshot": {
"href": "https://a.espncdn.com/i/headshots/womens-college-basketball/players/full/4900400.png",
"alt": "Kinley Fisher"
},
"jersey": "1",
"position": {
"name": "Guard",
"displayName": "Guard",
"abbreviation": "G"
}
},
"starter": true,
"didNotPlay": false,
"ejected": false,
"stats": [
"27",
"3-7",
"1-3",
"1-2",
"0",
"2",
"2",
"4",
"4",
"1",
"2",
"0",
"8"
]
},
{
"active": false,
"athlete": {
"id": "4899918",
"uid": "s:40~l:54~a:4899918",
"guid": "879ef461-d4ed-3dfc-af39-ecce8210f5ee",
"displayName": "Jade Upshaw",
"shortName": "J. Upshaw",
"links": [
{
"rel": [
"playercard",
"desktop",
"athlete"
],
"href": "https://www.espn.com/womens-college-basketball/player/_/id/4899918/jade-upshaw",
"text": "Player Card"
}
],
"headshot": {
"href": "https://a.espncdn.com/i/headshots/womens-college-basketball/players/full/4899918.png",
"alt": "Jade Upshaw"
},
"jersey": "0",
"position": {
"name": "Guard",
"displayName": "Guard",
"abbreviation": "G"
}
},
"starter": true,
"didNotPlay": false,
"ejected": false,
"stats": [
"29",
"7-14",
"3-8",
"2-3",
"3",
"5",
"8",
"4",
"1",
"1",
"4",
"5",
"19"
]
},
{
"active": false,
"athlete": {
"id": "5175438",
"uid": "s:40~l:54~a:5175438",
"guid": "00e57c66-5a5e-397f-8c8d-3ccd709812e2",
"displayName": "Cheyenne Banks",
"shortName": "C. Banks",
"links": [
{
"rel": [
"playercard",
"desktop",
"athlete"
],
"href": "https://www.espn.com/womens-college-basketball/player/_/id/5175438/cheyenne-banks",
"text": "Player Card"
}
],
"headshot": {
"href": "https://a.espncdn.com/i/headshots/womens-college-basketball/players/full/5175438.png",
"alt": "Cheyenne Banks"
},
"jersey": "42",
"position": {
"name": "Forward",
"displayName": "Forward",
"abbreviation": "F"
}
},
"starter": false,
"didNotPlay": false,
"ejected": false,
"stats": [
"19",
"2-3",
"0-0",
"1-1",
"0",
"3",
"3",
"0",
"0",
"0",
"0",
"2",
"5"
]
},
{
"active": false,
"athlete": {
"id": "5106797",
"uid": "s:40~l:54~a:5106797",
"guid": "fe33d3f5-e0ec-3491-8366-fc3c64649b7c",
"displayName": "Destine Duckworth",
"shortName": "D. Duckworth",
"links": [
{
"rel": [
"playercard",
"desktop",
"athlete"
],
"href": "https://www.espn.com/womens-college-basketball/player/_/id/5106797/destine-duckworth",
"text": "Player Card"
}
],
"headshot": {
"href": "https://a.espncdn.com/i/headshots/womens-college-basketball/players/full/5106797.png",
"alt": "Destine Duckworth"
},
"jersey": "12",
"position": {
"name": "Forward",
"displayName": "Forward",
"abbreviation": "F"
}
},
"starter": false,
"didNotPlay": false,
"ejected": false,
"stats": [
"10",
"1-4",
"1-2",
"0-0",
"0",
"1",
"1",
"1",
"0",
"0",
"0",
"2",
"3"
]
},
{
"active": false,
"athlete": {
"id": "5240581",
"uid": "s:40~l:54~a:5240581",
"guid": "c5599032-fd18-3d99-a434-4d839a230bb8",
"displayName": "Jenna Cook",
"shortName": "J. Cook",
"links": [
{
"rel": [
"playercard",
"desktop",
"athlete"
],
"href": "https://www.espn.com/womens-college-basketball/player/_/id/5240581/jenna-cook",
"text": "Player Card"
}
],
"headshot": {
"href": "https://a.espncdn.com/i/headshots/womens-college-basketball/players/full/5240581.png",
"alt": "Jenna Cook"
},
"jersey": "10",
"position": {
"name": "Guard",
"displayName": "Guard",
"abbreviation": "G"
}
},
"starter": false,
"didNotPlay": false,
"ejected": false,
"stats": [
"5",
"1-2",
"0-0",
"0-0",
"0",
"0",
"0",
"0",
"0",
"0",
"1",
"1",
"2"
]
},
{
"active": false,
"athlete": {
"id": "5175432",
"uid": "s:40~l:54~a:5175432",
"guid": "10e65702-7f96-3056-80c8-e080982dfdd1",
"displayName": "Cheyanne Kemp",
"shortName": "C. Kemp",
"links": [
{
"rel": [
"playercard",
"desktop",
"athlete"
],
"href": "https://www.espn.com/womens-college-basketball/player/_/id/5175432/cheyanne-kemp",
"text": "Player Card"
}
],
"headshot": {
"href": "https://a.espncdn.com/i/headshots/womens-college-basketball/players/full/5175432.png",
"alt": "Cheyanne Kemp"
},
"jersey": "4",
"position": {
"name": "Guard",
"displayName": "Guard",
"abbreviation": "G"
}
},
"starter": false,
"didNotPlay": false,
"ejected": false,
"stats": [
"16",
"1-6",
"0-2",
"0-0",
"1",
"0",
"1",
"0",
"2",
"0",
"0",
"1",
"2"
]
},
{
"active": false,
"athlete": {
"id": "4898916",
"uid": "s:40~l:54~a:4898916",
"guid": "e65788be-65da-3188-9cf0-3f41f28dc78b",
"displayName": "Randrea Wright",
"shortName": "R. Wright",
"links": [
{
"rel": [
"playercard",
"desktop",
"athlete"
],
"href": "https://www.espn.com/womens-college-basketball/player/_/id/4898916/randrea-wright",
"text": "Player Card"
}
],
"headshot": {
"href": "https://a.espncdn.com/i/headshots/womens-college-basketball/players/full/4898916.png",
"alt": "Randrea Wright"
},
"jersey": "3",
"position": {
"name": "Guard",
"displayName": "Guard",
"abbreviation": "G"
}
},
"starter": false,
"didNotPlay": false,
"ejected": false,
"stats": [
"16",
"2-2",
"0-0",
"2-3",
"0",
"0",
"0",
"1",
"0",
"0",
"2",
"1",
"6"
]
},
{
"active": false,
"athlete": {
"id": "5240582",
"uid": "s:40~l:54~a:5240582",
"guid": "0b108edb-dbe4-31eb-a96d-ba3a83234f33",
"displayName": "Kamryn Griffin",
"shortName": "K. Griffin",
"links": [
{
"rel": [
"playercard",
"desktop",
"athlete"
],
"href": "https://www.espn.com/womens-college-basketball/player/_/id/5240582/kamryn-griffin",
"text": "Player Card"
}
],
"headshot": {
"href": "https://a.espncdn.com/i/headshots/womens-college-basketball/players/full/5240582.png",
"alt": "Kamryn Griffin"
},
"jersey": "21",
"position": {
"name": "Forward",
"displayName": "Forward",
"abbreviation": "F"
}
},
"starter": false,
"didNotPlay": true,
"ejected": false,
"stats": []
},
{
"active": false,
"athlete": {
"id": "5175435",
"uid": "s:40~l:54~a:5175435",
"guid": "44a5fa5a-bf8f-341e-8568-9c742ca56b38",
"displayName": "Kaidyn Beckwith",
"shortName": "K. Beckwith",
"links": [
{
"rel": [
"playercard",
"desktop",
"athlete"
],
"href": "https://www.espn.com/womens-college-basketball/player/_/id/5175435/kaidyn-beckwith",
"text": "Player Card"
}
],
"headshot": {
"href": "https://a.espncdn.com/i/headshots/womens-college-basketball/players/full/5175435.png",
"alt": "Kaidyn Beckwith"
},
"jersey": "23",
"position": {
"name": "Guard",
"displayName": "Guard",
"abbreviation": "G"
}
},
"starter": false,
"didNotPlay": true,
"ejected": false,
"stats": []
}
],
"totals": [
"",
"30-57",
"8-21",
"6-9",
"9",
"31",
"40",
"18",
"11",
"10",
"17",
"20",
"74"
]
}
],
"displayOrder": 2
}
]
},
"format": {
"regulation": {
"periods": 4,
"displayName": "Quarter",
"slug": "quarter",
"clock": 600.0
},
"overtime": {
"clock": 300.0
}
},
"gameInfo": {
"venue": {
"id": "1908",
"fullName": "Farris Center",
"address": {
"city": "Conway",
"state": "AR"
},
"grass": false,
"images": []
},
"attendance": 673,
"officials": [
{
"fullName": "Shante Anderson",
"displayName": "Shante Anderson",
"position": {
"name": "Referee",
"displayName": "Referee",
"id": "40"
},
"order": 1
},
{
"fullName": "Meg Dallmann",
"displayName": "Meg Dallmann",
"position": {
"name": "Referee",
"displayName": "Referee",
"id": "40"
},
"order": 2
},
{
"fullName": "Tamires de Souza",
"displayName": "Tamires de Souza",
"position": {
"name": "Referee",
"displayName": "Referee",
"id": "40"
},
"order": 3
}
]
},
"leaders": [
{
"team": {
"id": "2110",
"uid": "s:40~l:54~t:2110",
"displayName": "Central Arkansas Sugar Bears",
"abbreviation": "CARK",
"links": [
{
"href": "https://www.espn.com/womens-college-basketball/team/_/id/2110/central-arkansas-sugar-bears",
"text": "Clubhouse"
},
{
"href": "https://www.espn.com/womens-college-basketball/team/schedule/_/id/2110",
"text": "Schedule"
}
],
"logo": "https://a.espncdn.com/i/teamlogos/ncaa/500/2110.png",
"logos": [
{
"href": "https://a.espncdn.com/i/teamlogos/ncaa/500/2110.png",
"width": 500,
"height": 500,
"alt": "",
"rel": [
"full",
"default"
],
"lastUpdated": "2018-10-04T14:41Z"
},
{
"href": "https://a.espncdn.com/i/teamlogos/ncaa/500-dark/2110.png",
"width": 500,
"height": 500,
"alt": "",
"rel": [
"full",
"dark"
],
"lastUpdated": "2018-10-04T14:41Z"
}
]
},
"leaders": [
{
"name": "points",
"displayName": "Points",
"leaders": [
{
"displayValue": "19",
"athlete": {
"id": "4899918",
"uid": "s:40~l:54~a:4899918",
"guid": "879ef461-d4ed-3dfc-af39-ecce8210f5ee",
"lastName": "Upshaw",
"fullName": "Jade Upshaw",
"displayName": "Jade Upshaw",
"shortName": "J. Upshaw",
"links": [
{
"rel": [
"playercard",
"desktop",
"athlete"
],
"href": "https://www.espn.com/womens-college-basketball/player/_/id/4899918/jade-upshaw",
"text": "Player Card"
}
],
"headshot": {
"href": "https://a.espncdn.com/i/headshots/womens-college-basketball/players/full/4899918.png",
"alt": "Jade Upshaw"
},
"jersey": "0",
"position": {
"abbreviation": "G"
},
"status": {
"id": "1",
"name": "Active",
"type": "active",
"abbreviation": "Active"
}
},
"statistics": [
{
"name": "points",
"displayName": "Points",
"shortDisplayName": "PTS",
"description": "The number of points scored.",
"abbreviation": "PTS",
"value": 19.0,
"displayValue": "19"
},
{
"name": "fieldGoals",
"displayName": "Field Goals",
"shortDisplayName": "FG",
"description": "Field Goal makes and attempts.",
"abbreviation": "FG",
"value": 0.5,
"displayValue": "7/14"
},
{
"name": "freeThrows",
"displayName": "Free Throws",
"shortDisplayName": "FT",
"description": "Free Throw makes and attempts.",
"abbreviation": "FT",
"value": 0.666667,
"displayValue": "2/3"
}
]
}
]
},
{
"name": "assists",
"displayName": "Assists",
"leaders": [
{
"displayValue": "4",
"athlete": {
"id": "4899918",
"uid": "s:40~l:54~a:4899918",
"guid": "879ef461-d4ed-3dfc-af39-ecce8210f5ee",
"lastName": "Upshaw",
"fullName": "Jade Upshaw",
"displayName": "Jade Upshaw",
"shortName": "J. Upshaw",
"links": [
{
"rel": [
"playercard",
"desktop",
"athlete"
],
"href": "https://www.espn.com/womens-college-basketball/player/_/id/4899918/jade-upshaw",
"text": "Player Card"
}
],
"headshot": {
"href": "https://a.espncdn.com/i/headshots/womens-college-basketball/players/full/4899918.png",
"alt": "Jade Upshaw"
},
"jersey": "0",
"position": {
"abbreviation": "G"
},
"status": {
"id": "1",
"name": "Active",
"type": "active",
"abbreviation": "Active"
}
},
"statistics": [
{
"name": "assists",
"displayName": "Assists",
"shortDisplayName": "AST",
"description": "The number of times a player who passes the ball to a teammate in a way that leads to a score by field goal, meaning that he or she was \"assisting\" in the basket. There is some judgment involved in deciding whether a passer should be credited with an assist.",
"abbreviation": "AST",
"value": 4.0,
"displayValue": "4"
},
{
"name": "turnovers",
"displayName": "Turnovers",
"shortDisplayName": "TO",
"description": "The number of times a player loses possession to the other team.",
"abbreviation": "TO",
"value": 4.0,
"displayValue": "4"
},
{
"name": "minutes",
"displayName": "Minutes",
"shortDisplayName": "MIN",
"description": "The total number of minutes played.",
"abbreviation": "MIN",
"value": 29.0,
"displayValue": "29"
},
{
"name": "assistTurnoverRatio",
"displayName": "Assist To Turnover Ratio",
"shortDisplayName": "AST/TO",
"description": "The average number of assists a player or team records per turnover",
"abbreviation": "AST/TO",
"value": 1.0,
"displayValue": "1.0"
}
]
}
]
},
{
"name": "rebounds",
"displayName": "Rebounds",
"leaders": [
{
"displayValue": "9",
"athlete": {
"id": "5175433",
"uid": "s:40~l:54~a:5175433",
"guid": "22526e48-d7ee-3f04-bc28-d32c9963efdf",
"lastName": "Stephens",
"fullName": "Bree Stephens",
"displayName": "Bree Stephens",
"shortName": "B. Stephens",
"links": [
{
"rel": [
"playercard",
"desktop",
"athlete"
],
"href": "https://www.espn.com/womens-college-basketball/player/_/id/5175433/bree-stephens",
"text": "Player Card"
}
],
"headshot": {
"href": "https://a.espncdn.com/i/headshots/womens-college-basketball/players/full/5175433.png",
"alt": "Bree Stephens"
},
"jersey": "5",
"position": {
"abbreviation": "F"
},
"status": {
"id": "1",
"name": "Active",
"type": "active",
"abbreviation": "Active"
}
},
"statistics": [
{
"name": "rebounds",
"displayName": "Rebounds",
"shortDisplayName": "REB",
"description": "The total number of rebounds (offensive and defensive).",
"abbreviation": "REB",
"value": 9.0,
"displayValue": "9"
},
{
"name": "defensiveRebounds",
"displayName": "Defensive Rebounds",
"shortDisplayName": "DREB",
"description": "The number of times when the defense obtains the possession of the ball after a missed shot by the offense.",
"abbreviation": "DR",
"value": 7.0,
"displayValue": "7"
},
{
"name": "offensiveRebounds",
"displayName": "Offensive Rebounds",
"shortDisplayName": "OREB",
"description": "The number of times when the offense obtains the possession of the ball after a missed shot.",
"abbreviation": "OR",
"value": 2.0,
"displayValue": "2"
}
]
}
]
}
]
},
{
"team": {
"id": "294",
"uid": "s:40~l:54~t:294",
"displayName": "Jacksonville Dolphins",
"abbreviation": "JAX",
"links": [
{
"href": "https://www.espn.com/womens-college-basketball/team/_/id/294/jacksonville-dolphins",
"text": "Clubhouse"
},
{
"href": "https://www.espn.com/womens-college-basketball/team/schedule/_/id/294",
"text": "Schedule"
}
],
"logo": "https://a.espncdn.com/i/teamlogos/ncaa/500/294.png",
"logos": [
{
"href": "https://a.espncdn.com/i/teamlogos/ncaa/500/294.png",
"width": 500,
"height": 500,
"alt": "",
"rel": [
"full",
"default"
],
"lastUpdated": "2018-10-22T17:25Z"
},
{
"href": "https://a.espncdn.com/i/teamlogos/ncaa/500-dark/294.png",
"width": 500,
"height": 500,
"alt": "",
"rel": [
"full",
"dark"
],
"lastUpdated": "2018-10-22T17:26Z"
}
]
},
"leaders": [
{
"name": "points",
"displayName": "Points",
"leaders": [
{
"displayValue": "18",
"athlete": {
"id": "4595196",
"uid": "s:40~l:54~a:4595196",
"guid": "96880aa3-b13e-3238-b572-e49cb796ceb1",
"lastName": "Edwards",
"fullName": "Makayla Edwards",
"displayName": "Makayla Edwards",
"shortName": "M. Edwards",
"links": [
{
"rel": [
"playercard",
"desktop",
"athlete"
],
"href": "https://www.espn.com/womens-college-basketball/player/_/id/4595196/makayla-edwards",
"text": "Player Card"
}
],
"headshot": {
"href": "https://a.espncdn.com/i/headshots/womens-college-basketball/players/full/4595196.png",
"alt": "Makayla Edwards"
},
"jersey": "4",
"position": {
"abbreviation": "F"
},
"status": {
"id": "1",
"name": "Active",
"type": "active",
"abbreviation": "Active"
}
},
"statistics": [
{
"name": "points",
"displayName": "Points",
"shortDisplayName": "PTS",
"description": "The number of points scored.",
"abbreviation": "PTS",
"value": 18.0,
"displayValue": "18"
},
{
"name": "fieldGoals",
"displayName": "Field Goals",
"shortDisplayName": "FG",
"description": "Field Goal makes and attempts.",
"abbreviation": "FG",
"value": 0.411765,
"displayValue": "7/17"
},
{
"name": "freeThrows",
"displayName": "Free Throws",
"shortDisplayName": "FT",
"description": "Free Throw makes and attempts.",
"abbreviation": "FT",
"value": 0.333333,
"displayValue": "2/6"
}
]
}
]
},
{
"name": "assists",
"displayName": "Assists",
"leaders": [
{
"displayValue": "3",
"athlete": {
"id": "4433734",
"uid": "s:40~l:54~a:4433734",
"guid": "919144bb-6502-3aad-8c89-f84b208fec04",
"lastName": "Williams",
"fullName": "Priscilla Williams",
"displayName": "Priscilla Williams",
"shortName": "P. Williams",
"links": [
{
"rel": [
"playercard",
"desktop",
"athlete"
],
"href": "https://www.espn.com/womens-college-basketball/player/_/id/4433734/priscilla-williams",
"text": "Player Card"
}
],
"headshot": {
"href": "https://a.espncdn.com/i/headshots/womens-college-basketball/players/full/4433734.png",
"alt": "Priscilla Williams"
},
"jersey": "23",
"position": {
"abbreviation": "G"
},
"status": {
"id": "1",
"name": "Active",
"type": "active",
"abbreviation": "Active"
}
},
"statistics": [
{
"name": "assists",
"displayName": "Assists",
"shortDisplayName": "AST",
"description": "The number of times a player who passes the ball to a teammate in a way that leads to a score by field goal, meaning that he or she was \"assisting\" in the basket. There is some judgment involved in deciding whether a passer should be credited with an assist.",
"abbreviation": "AST",
"value": 3.0,
"displayValue": "3"
},
{
"name": "turnovers",
"displayName": "Turnovers",
"shortDisplayName": "TO",
"description": "The number of times a player loses possession to the other team.",
"abbreviation": "TO",
"value": 5.0,
"displayValue": "5"
},
{
"name": "minutes",
"displayName": "Minutes",
"shortDisplayName": "MIN",
"description": "The total number of minutes played.",
"abbreviation": "MIN",
"value": 33.0,
"displayValue": "33"
},
{
"name": "assistTurnoverRatio",
"displayName": "Assist To Turnover Ratio",
"shortDisplayName": "AST/TO",
"description": "The average number of assists a player or team records per turnover",
"abbreviation": "AST/TO",
"value": 0.6,
"displayValue": "0.6"
}
]
}
]
},
{
"name": "rebounds",
"displayName": "Rebounds",
"leaders": [
{
"displayValue": "15",
"athlete": {
"id": "5175447",
"uid": "s:40~l:54~a:5175447",
"guid": "1d1475b9-2478-3610-b6d9-135abb1535eb",
"lastName": "Craig",
"fullName": "Saniyah Craig",
"displayName": "Saniyah Craig",
"shortName": "S. Craig",
"links": [
{
"rel": [
"playercard",
"desktop",
"athlete"
],
"href": "https://www.espn.com/womens-college-basketball/player/_/id/5175447/saniyah-craig",
"text": "Player Card"
}
],
"headshot": {
"href": "https://a.espncdn.com/i/headshots/womens-college-basketball/players/full/5175447.png",
"alt": "Saniyah Craig"
},
"jersey": "15",
"position": {
"abbreviation": "F"
},
"status": {
"id": "1",
"name": "Active",
"type": "active",
"abbreviation": "Active"
}
},
"statistics": [
{
"name": "rebounds",
"displayName": "Rebounds",
"shortDisplayName": "REB",
"description": "The total number of rebounds (offensive and defensive).",
"abbreviation": "REB",
"value": 15.0,
"displayValue": "15"
},
{
"name": "defensiveRebounds",
"displayName": "Defensive Rebounds",
"shortDisplayName": "DREB",
"description": "The number of times when the defense obtains the possession of the ball after a missed shot by the offense.",
"abbreviation": "DR",
"value": 9.0,
"displayValue": "9"
},
{
"name": "offensiveRebounds",
"displayName": "Offensive Rebounds",
"shortDisplayName": "OREB",
"description": "The number of times when the offense obtains the possession of the ball after a missed shot.",
"abbreviation": "OR",
"value": 6.0,
"displayValue": "6"
}
]
}
]
}
]
}
],
"broadcasts": [
{
"type": {
"id": "4",
"shortName": "Streaming",
"longName": "Streaming",
"slug": "streaming"
},
"station": "ESPN+",
"market": {
"id": "1",
"type": "National"
},
"media": {
"callLetters": "ESPN+",
"name": "ESPN+",
"shortName": "ESPN+"
},
"lang": "en",
"region": "us"
}
],
"predictor": {
"header": "Matchup Predictor",
"homeTeam": {
"id": "2110",
"gameProjection": "81.0",
"teamChanceLoss": "19.0",
"teamChanceTie": "0.0"
},
"awayTeam": {
"id": "294",
"gameProjection": "19.0",
"teamChanceLoss": "81.0",
"teamChanceTie": "0.0"
}
},
"pickcenter": [],
"againstTheSpread": [
{
"team": {
"id": "294",
"uid": "s:40~l:54~t:294",
"displayName": "Jacksonville Dolphins",
"abbreviation": "JAX",
"links": [
{
"href": "https://www.espn.com/womens-college-basketball/team/_/id/294/jacksonville-dolphins",
"text": "Clubhouse"
},
{
"href": "https://www.espn.com/womens-college-basketball/team/schedule/_/id/294",
"text": "Schedule"
}
],
"logo": "https://a.espncdn.com/i/teamlogos/ncaa/500/294.png",
"logos": [
{
"href": "https://a.espncdn.com/i/teamlogos/ncaa/500/294.png",
"width": 500,
"height": 500,
"alt": "",
"rel": [
"full",
"default"
],
"lastUpdated": "2018-10-22T17:25Z"
},
{
"href": "https://a.espncdn.com/i/teamlogos/ncaa/500-dark/294.png",
"width": 500,
"height": 500,
"alt": "",
"rel": [
"full",
"dark"
],
"lastUpdated": "2018-10-22T17:26Z"
}
]
},
"records": []
},
{
"team": {
"id": "2110",
"uid": "s:40~l:54~t:2110",
"displayName": "Central Arkansas Sugar Bears",
"abbreviation": "CARK",
"links": [
{
"href": "https://www.espn.com/womens-college-basketball/team/_/id/2110/central-arkansas-sugar-bears",
"text": "Clubhouse"
},
{
"href": "https://www.espn.com/womens-college-basketball/team/schedule/_/id/2110",
"text": "Schedule"
}
],
"logo": "https://a.espncdn.com/i/teamlogos/ncaa/500/2110.png",
"logos": [
{
"href": "https://a.espncdn.com/i/teamlogos/ncaa/500/2110.png",
"width": 500,
"height": 500,
"alt": "",
"rel": [
"full",
"default"
],
"lastUpdated": "2018-10-04T14:41Z"
},
{
"href": "https://a.espncdn.com/i/teamlogos/ncaa/500-dark/2110.png",
"width": 500,
"height": 500,
"alt": "",
"rel": [
"full",
"dark"
],
"lastUpdated": "2018-10-04T14:41Z"
}
]
},
"records": []
}
],
"odds": [],
"winprobability": {},
"header": {
"id": "401713942",
"uid": "s:40~l:54~e:401713942",
"season": {
"year": 2025,
"type": 2
},
"timeValid": true,
"competitions": [
{
"id": "401713942",
"uid": "s:40~l:54~e:401713942~c:401713942",
"date": "2025-01-02T23:00Z",
"neutralSite": false,
"conferenceCompetition": true,
"boxscoreAvailable": true,
"commentaryAvailable": false,
"liveAvailable": false,
"shotChartAvailable": false,
"timeoutsAvailable": false,
"possessionArrowAvailable": false,
"onWatchESPN": true,
"recent": false,
"wallclockAvailable": false,
"boxscoreSource": "full",
"playByPlaySource": "none",
"competitors": [
{
"id": "2110",
"uid": "s:40~l:54~t:2110",
"order": 0,
"homeAway": "home",
"winner": true,
"team": {
"id": "2110",
"uid": "s:40~l:54~t:2110",
"location": "Central Arkansas",
"name": "Sugar Bears",
"nickname": "C Arkansas",
"abbreviation": "CARK",
"displayName": "Central Arkansas Sugar Bears",
"color": "a7a9ac",
"alternateColor": "8e959a",
"logos": [
{
"href": "https://a.espncdn.com/i/teamlogos/ncaa/500/2110.png",
"width": 500,
"height": 500,
"alt": "",
"rel": [
"full",
"default"
],
"lastUpdated": "2018-10-04T14:41Z"
},
{
"href": "https://a.espncdn.com/i/teamlogos/ncaa/500-dark/2110.png",
"width": 500,
"height": 500,
"alt": "",
"rel": [
"full",
"dark"
],
"lastUpdated": "2018-10-04T14:41Z"
},
{
"href": "https://a.espncdn.com/guid/3422b720-1f49-7a40-1ba5-e509f8713ce5/logos/primary_logo_on_white_color.png",
"width": 4096,
"height": 4096,
"alt": "",
"rel": [
"full",
"primary_logo_on_white_color"
],
"lastUpdated": "2024-11-11T01:17Z"
},
{
"href": "https://a.espncdn.com/guid/3422b720-1f49-7a40-1ba5-e509f8713ce5/logos/primary_logo_on_black_color.png",
"width": 4096,
"height": 4096,
"alt": "",
"rel": [
"full",
"primary_logo_on_black_color"
],
"lastUpdated": "2024-11-11T01:17Z"
},
{
"href": "https://a.espncdn.com/guid/3422b720-1f49-7a40-1ba5-e509f8713ce5/logos/primary_logo_on_primary_color.png",
"width": 4096,
"height": 4096,
"alt": "",
"rel": [
"full",
"primary_logo_on_primary_color"
],
"lastUpdated": "2024-11-11T01:17Z"
},
{
"href": "https://a.espncdn.com/guid/3422b720-1f49-7a40-1ba5-e509f8713ce5/logos/primary_logo_on_secondary_color.png",
"width": 4096,
"height": 4096,
"alt": "",
"rel": [
"full",
"primary_logo_on_secondary_color"
],
"lastUpdated": "2024-11-11T01:17Z"
},
{
"href": "https://a.espncdn.com/guid/3422b720-1f49-7a40-1ba5-e509f8713ce5/logos/secondary_logo_on_white_color.png",
"width": 4096,
"height": 4096,
"alt": "",
"rel": [
"full",
"secondary_logo_on_white_color"
],
"lastUpdated": "2024-11-11T01:17Z"
},
{
"href": "https://a.espncdn.com/guid/3422b720-1f49-7a40-1ba5-e509f8713ce5/logos/secondary_logo_on_black_color.png",
"width": 4096,
"height": 4096,
"alt": "",
"rel": [
"full",
"secondary_logo_on_black_color"
],
"lastUpdated": "2024-11-11T01:17Z"
},
{
"href": "https://a.espncdn.com/guid/3422b720-1f49-7a40-1ba5-e509f8713ce5/logos/secondary_logo_on_primary_color.png",
"width": 4096,
"height": 4096,
"alt": "",
"rel": [
"full",
"secondary_logo_on_primary_color"
],
"lastUpdated": "2024-11-11T01:17Z"
},
{
"href": "https://a.espncdn.com/guid/3422b720-1f49-7a40-1ba5-e509f8713ce5/logos/secondary_logo_on_secondary_color.png",
"width": 4096,
"height": 4096,
"alt": "",
"rel": [
"full",
"secondary_logo_on_secondary_color"
],
"lastUpdated": "2024-11-11T01:17Z"
}
],
"links": [
{
"rel": [
"clubhouse",
"desktop",
"team"
],
"href": "https://www.espn.com/womens-college-basketball/team/_/id/2110/central-arkansas-sugar-bears",
"text": "Clubhouse"
}
]
},
"score": "74",
"linescores": [
{
"displayValue": "26"
},
{
"displayValue": "18"
},
{
"displayValue": "14"
},
{
"displayValue": "16"
}
],
"record": [
{
"type": "total",
"summary": "7-5",
"displayValue": "7-5"
},
{
"type": "home",
"summary": "5-0",
"displayValue": "5-0"
},
{
"type": "vsconf",
"summary": "1-0",
"displayValue": "1-0"
}
],
"possession": false
},
{
"id": "294",
"uid": "s:40~l:54~t:294",
"order": 1,
"homeAway": "away",
"winner": false,
"team": {
"id": "294",
"uid": "s:40~l:54~t:294",
"location": "Jacksonville",
"name": "Dolphins",
"nickname": "Jacksonville",
"abbreviation": "JAX",
"displayName": "Jacksonville Dolphins",
"color": "00523e",
"logos": [
{
"href": "https://a.espncdn.com/i/teamlogos/ncaa/500/294.png",
"width": 500,
"height": 500,
"alt": "",
"rel": [
"full",
"default"
],
"lastUpdated": "2018-10-22T17:25Z"
},
{
"href": "https://a.espncdn.com/i/teamlogos/ncaa/500-dark/294.png",
"width": 500,
"height": 500,
"alt": "",
"rel": [
"full",
"dark"
],
"lastUpdated": "2018-10-22T17:26Z"
},
{
"href": "https://a.espncdn.com/guid/d059e9f4-9149-f5a3-0dd3-4577f966ba85/logos/primary_logo_on_white_color.png",
"width": 4096,
"height": 4096,
"alt": "",
"rel": [
"full",
"primary_logo_on_white_color"
],
"lastUpdated": "2024-11-11T01:45Z"
},
{
"href": "https://a.espncdn.com/guid/d059e9f4-9149-f5a3-0dd3-4577f966ba85/logos/primary_logo_on_black_color.png",
"width": 4096,
"height": 4096,
"alt": "",
"rel": [
"full",
"primary_logo_on_black_color"
],
"lastUpdated": "2024-11-11T01:45Z"
},
{
"href": "https://a.espncdn.com/guid/d059e9f4-9149-f5a3-0dd3-4577f966ba85/logos/primary_logo_on_primary_color.png",
"width": 4096,
"height": 4096,
"alt": "",
"rel": [
"full",
"primary_logo_on_primary_color"
],
"lastUpdated": "2024-11-11T01:45Z"
},
{
"href": "https://a.espncdn.com/guid/d059e9f4-9149-f5a3-0dd3-4577f966ba85/logos/primary_logo_on_secondary_color.png",
"width": 4096,
"height": 4096,
"alt": "",
"rel": [
"full",
"primary_logo_on_secondary_color"
],
"lastUpdated": "2024-11-11T01:45Z"
},
{
"href": "https://a.espncdn.com/guid/d059e9f4-9149-f5a3-0dd3-4577f966ba85/logos/secondary_logo_on_white_color.png",
"width": 4096,
"height": 4096,
"alt": "",
"rel": [
"full",
"secondary_logo_on_white_color"
],
"lastUpdated": "2024-11-11T01:45Z"
},
{
"href": "https://a.espncdn.com/guid/d059e9f4-9149-f5a3-0dd3-4577f966ba85/logos/secondary_logo_on_black_color.png",
"width": 4096,
"height": 4096,
"alt": "",
"rel": [
"full",
"secondary_logo_on_black_color"
],
"lastUpdated": "2024-11-11T01:45Z"
},
{
"href": "https://a.espncdn.com/guid/d059e9f4-9149-f5a3-0dd3-4577f966ba85/logos/secondary_logo_on_primary_color.png",
"width": 4096,
"height": 4096,
"alt": "",
"rel": [
"full",
"secondary_logo_on_primary_color"
],
"lastUpdated": "2024-11-11T01:45Z"
},
{
"href": "https://a.espncdn.com/guid/d059e9f4-9149-f5a3-0dd3-4577f966ba85/logos/secondary_logo_on_secondary_color.png",
"width": 4096,
"height": 4096,
"alt": "",
"rel": [
"full",
"secondary_logo_on_secondary_color"
],
"lastUpdated": "2024-11-11T01:45Z"
}
],
"links": [
{
"rel": [
"clubhouse",
"desktop",
"team"
],
"href": "https://www.espn.com/womens-college-basketball/team/_/id/294/jacksonville-dolphins",
"text": "Clubhouse"
}
]
},
"score": "63",
"linescores": [
{
"displayValue": "9"
},
{
"displayValue": "21"
},
{
"displayValue": "21"
},
{
"displayValue": "12"
}
],
"record": [
{
"type": "total",
"summary": "6-7",
"displayValue": "6-7"
},
{
"type": "road",
"summary": "2-6",
"displayValue": "2-6"
},
{
"type": "vsconf",
"summary": "0-1",
"displayValue": "0-1"
}
],
"possession": false
}
],
"status": {
"type": {
"id": "3",
"name": "STATUS_FINAL",
"state": "post",
"completed": true,
"description": "Final",
"detail": "Final",
"shortDetail": "Final"
}
},
"broadcasts": [
{
"type": {
"id": "4",
"shortName": "Streaming"
},
"market": {
"id": "1",
"type": "National"
},
"media": {
"shortName": "ESPN+"
},
"lang": "en",
"region": "us"
}
],
"groups": {
"id": "46",
"name": "ASUN Conference",
"abbreviation": "a-sun",
"shortName": "ASUN",
"midsizeName": "ASUN"
}
}
],
"links": [
{
"rel": [
"summary",
"desktop",
"event"
],
"href": "https://www.espn.com/womens-college-basketball/game/_/gameId/401713942/jacksonville-c-arkansas",
"text": "Gamecast",
"shortText": "Summary",
"isExternal": false,
"isPremium": false
},
{
"rel": [
"boxscore",
"desktop",
"event"
],
"href": "https://www.espn.com/womens-college-basketball/boxscore/_/gameId/401713942",
"text": "Box Score",
"shortText": "Box Score",
"isExternal": false,
"isPremium": false
},
{
"rel": [
"teamstats",
"desktop",
"event"
],
"href": "https://www.espn.com/womens-college-basketball/matchup?gameId=401713942",
"text": "Team Stats",
"shortText": "Team Stats",
"isExternal": false,
"isPremium": false
}
],
"week": 9,
"league": {
"id": "54",
"uid": "s:40~l:54",
"name": "NCAA Women's Basketball",
"abbreviation": "NCAAW",
"midsizeName": "NCAAW Basketball",
"slug": "womens-college-basketball",
"isTournament": false,
"links": [
{
"rel": [
"index",
"desktop",
"league"
],
"href": "https://www.espn.com/womens-college-basketball/",
"text": "Index"
},
{
"rel": [
"index",
"sportscenter",
"app",
"league"
],
"href": "sportscenter://x-callback-url/showClubhouse?uid=s:40~l:54",
"text": "Index"
},
{
"rel": [
"schedule",
"desktop",
"league"
],
"href": "https://www.espn.com/womens-college-basketball/schedule",
"text": "Schedule"
},
{
"rel": [
"schedule",
"sportscenter",
"app",
"league"
],
"href": "sportscenter://x-callback-url/showClubhouse?uid=s:40~l:54&section=scores",
"text": "Schedule"
},
{
"rel": [
"standings",
"desktop",
"league"
],
"href": "https://www.espn.com/womens-college-basketball/standings",
"text": "Standings"
},
{
"rel": [
"standings",
"sportscenter",
"app",
"league"
],
"href": "sportscenter://x-callback-url/showClubhouse?uid=s:40~l:54&section=standings",
"text": "Standings"
},
{
"rel": [
"rankings",
"desktop",
"league"
],
"href": "https://www.espn.com/womens-college-basketball/rankings",
"text": "Rankings"
},
{
"rel": [
"scores",
"desktop",
"league"
],
"href": "https://www.espn.com/womens-college-basketball/scoreboard",
"text": "Scores"
},
{
"rel": [
"scores",
"sportscenter",
"app",
"league"
],
"href": "sportscenter://x-callback-url/showClubhouse?uid=s:40~l:54&section=scores",
"text": "Scores"
},
{
"rel": [
"stats",
"desktop",
"league"
],
"href": "https://www.espn.com/womens-college-basketball/stats",
"text": "Stats"
},
{
"rel": [
"teams",
"desktop",
"league"
],
"href": "https://www.espn.com/womens-college-basketball/teams",
"text": "Teams"
},
{
"rel": [
"injuries",
"desktop",
"league"
],
"href": "https://www.espn.com/womens-college-basketball/injuries",
"text": "Injuries"
},
{
"rel": [
"odds",
"desktop",
"league"
],
"href": "https://www.espn.com/womens-college-basketball/odds",
"text": "Odds"
},
{
"rel": [
"odds",
"sportscenter",
"app",
"league"
],
"href": "sportscenter://x-callback-url/showClubhouse?uid=s:40~l:54&section=odds",
"text": "Odds"
}
]
}
},
"plays": [],
"article": [],
"videos": [],
"standings": {
"fullViewLink": {
"text": "Full Standings",
"href": "https://www.espn.com/womens-college-basketball/standings"
},
"header": "2025 Standings",
"groups": [
{
"standings": {
"entries": [
{
"team": "Florida Gulf Coast",
"link": "https://www.espn.com/womens-college-basketball/team/_/id/526/florida-gulf-coast-eagles",
"id": "526",
"uid": "s:40~l:54~t:526",
"stats": [
{
"id": "0",
"name": "overall",
"abbreviation": "Season",
"displayName": "Team Season Record",
"shortDisplayName": "Season",
"description": "Overall Record",
"type": "total",
"summary": "22-3",
"displayValue": "22-3"
},
{
"name": "gamesBehind",
"displayName": "Games Back",
"shortDisplayName": "GB",
"description": "Games Back",
"abbreviation": "GB",
"type": "vsconf_gamesbehind",
"value": 0.0,
"displayValue": "-"
},
{
"id": "9",
"name": "vs. Conf.",
"abbreviation": "VS CONF",
"displayName": "CONF",
"shortDisplayName": "CONF",
"description": "Conference Record",
"type": "vsconf",
"summary": "13-0",
"displayValue": "13-0"
}
],
"logo": [
{
"href": "https://a.espncdn.com/i/teamlogos/ncaa/500/526.png",
"width": 500,
"height": 500,
"alt": "",
"rel": [
"full",
"default"
],
"lastUpdated": "2018-06-05T12:08Z"
},
{
"href": "https://a.espncdn.com/i/teamlogos/ncaa/500-dark/526.png",
"width": 500,
"height": 500,
"alt": "",
"rel": [
"full",
"dark"
],
"lastUpdated": "2018-06-05T12:08Z"
}
]
},
{
"team": "Central Arkansas",
"link": "https://www.espn.com/womens-college-basketball/team/_/id/2110/central-arkansas-sugar-bears",
"id": "2110",
"uid": "s:40~l:54~t:2110",
"stats": [
{
"id": "0",
"name": "overall",
"abbreviation": "Season",
"displayName": "Team Season Record",
"shortDisplayName": "Season",
"description": "Overall Record",
"type": "total",
"summary": "18-6",
"displayValue": "18-6"
},
{
"name": "gamesBehind",
"displayName": "Games Back",
"shortDisplayName": "GB",
"description": "Games Back",
"abbreviation": "GB",
"type": "vsconf_gamesbehind",
"value": 1.0,
"displayValue": "1"
},
{
"id": "9",
"name": "vs. Conf.",
"abbreviation": "VS CONF",
"displayName": "CONF",
"shortDisplayName": "CONF",
"description": "Conference Record",
"type": "vsconf",
"summary": "12-1",
"displayValue": "12-1"
}
],
"logo": [
{
"href": "https://a.espncdn.com/i/teamlogos/ncaa/500/2110.png",
"width": 500,
"height": 500,
"alt": "",
"rel": [
"full",
"default"
],
"lastUpdated": "2018-10-04T14:41Z"
},
{
"href": "https://a.espncdn.com/i/teamlogos/ncaa/500-dark/2110.png",
"width": 500,
"height": 500,
"alt": "",
"rel": [
"full",
"dark"
],
"lastUpdated": "2018-10-04T14:41Z"
}
]
},
{
"team": "Lipscomb",
"link": "https://www.espn.com/womens-college-basketball/team/_/id/288/lipscomb-bisons",
"id": "288",
"uid": "s:40~l:54~t:288",
"stats": [
{
"id": "0",
"name": "overall",
"abbreviation": "Season",
"displayName": "Team Season Record",
"shortDisplayName": "Season",
"description": "Overall Record",
"type": "total",
"summary": "15-8",
"displayValue": "15-8"
},
{
"name": "gamesBehind",
"displayName": "Games Back",
"shortDisplayName": "GB",
"description": "Games Back",
"abbreviation": "GB",
"type": "vsconf_gamesbehind",
"value": 4.5,
"displayValue": "4.5"
},
{
"id": "9",
"name": "vs. Conf.",
"abbreviation": "VS CONF",
"displayName": "CONF",
"shortDisplayName": "CONF",
"description": "Conference Record",
"type": "vsconf",
"summary": "8-4",
"displayValue": "8-4"
}
],
"logo": [
{
"href": "https://a.espncdn.com/i/teamlogos/ncaa/500/288.png",
"width": 500,
"height": 500,
"alt": "",
"rel": [
"full",
"default"
],
"lastUpdated": "2018-06-05T12:08Z"
},
{
"href": "https://a.espncdn.com/i/teamlogos/ncaa/500-dark/288.png",
"width": 500,
"height": 500,
"alt": "",
"rel": [
"full",
"dark"
],
"lastUpdated": "2018-06-05T12:08Z"
}
]
},
{
"team": "Stetson",
"link": "https://www.espn.com/womens-college-basketball/team/_/id/56/stetson-hatters",
"id": "56",
"uid": "s:40~l:54~t:56",
"stats": [
{
"id": "0",
"name": "overall",
"abbreviation": "Season",
"displayName": "Team Season Record",
"shortDisplayName": "Season",
"description": "Overall Record",
"type": "total",
"summary": "14-11",
"displayValue": "14-11"
},
{
"name": "gamesBehind",
"displayName": "Games Back",
"shortDisplayName": "GB",
"description": "Games Back",
"abbreviation": "GB",
"type": "vsconf_gamesbehind",
"value": 5.0,
"displayValue": "5"
},
{
"id": "9",
"name": "vs. Conf.",
"abbreviation": "VS CONF",
"displayName": "CONF",
"shortDisplayName": "CONF",
"description": "Conference Record",
"type": "vsconf",
"summary": "8-5",
"displayValue": "8-5"
}
],
"logo": [
{
"href": "https://a.espncdn.com/i/teamlogos/ncaa/500/56.png",
"width": 500,
"height": 500,
"alt": "",
"rel": [
"full",
"default"
],
"lastUpdated": "2019-10-21T16:39Z"
},
{
"href": "https://a.espncdn.com/i/teamlogos/ncaa/500-dark/56.png",
"width": 500,
"height": 500,
"alt": "",
"rel": [
"full",
"dark"
],
"lastUpdated": "2019-10-21T16:39Z"
}
]
},
{
"team": "Eastern Kentucky",
"link": "https://www.espn.com/womens-college-basketball/team/_/id/2198/eastern-kentucky-colonels",
"id": "2198",
"uid": "s:40~l:54~t:2198",
"stats": [
{
"id": "0",
"name": "overall",
"abbreviation": "Season",
"displayName": "Team Season Record",
"shortDisplayName": "Season",
"description": "Overall Record",
"type": "total",
"summary": "17-9",
"displayValue": "17-9"
},
{
"name": "gamesBehind",
"displayName": "Games Back",
"shortDisplayName": "GB",
"description": "Games Back",
"abbreviation": "GB",
"type": "vsconf_gamesbehind",
"value": 6.0,
"displayValue": "6"
},
{
"id": "9",
"name": "vs. Conf.",
"abbreviation": "VS CONF",
"displayName": "CONF",
"shortDisplayName": "CONF",
"description": "Conference Record",
"type": "vsconf",
"summary": "7-6",
"displayValue": "7-6"
}
],
"logo": [
{
"href": "https://a.espncdn.com/i/teamlogos/ncaa/500/2198.png",
"width": 500,
"height": 500,
"alt": "",
"rel": [
"full",
"default"
],
"lastUpdated": "2019-08-13T14:33Z"
},
{
"href": "https://a.espncdn.com/i/teamlogos/ncaa/500-dark/2198.png",
"width": 500,
"height": 500,
"alt": "",
"rel": [
"full",
"dark"
],
"lastUpdated": "2019-08-13T14:38Z"
}
]
},
{
"team": "North Alabama",
"link": "https://www.espn.com/womens-college-basketball/team/_/id/2453/north-alabama-lions",
"id": "2453",
"uid": "s:40~l:54~t:2453",
"stats": [
{
"id": "0",
"name": "overall",
"abbreviation": "Season",
"displayName": "Team Season Record",
"shortDisplayName": "Season",
"description": "Overall Record",
"type": "total",
"summary": "12-12",
"displayValue": "12-12"
},
{
"name": "gamesBehind",
"displayName": "Games Back",
"shortDisplayName": "GB",
"description": "Games Back",
"abbreviation": "GB",
"type": "vsconf_gamesbehind",
"value": 6.0,
"displayValue": "6"
},
{
"id": "9",
"name": "vs. Conf.",
"abbreviation": "VS CONF",
"displayName": "CONF",
"shortDisplayName": "CONF",
"description": "Conference Record",
"type": "vsconf",
"summary": "7-6",
"displayValue": "7-6"
}
],
"logo": [
{
"href": "https://a.espncdn.com/i/teamlogos/ncaa/500/2453.png",
"width": 500,
"height": 500,
"alt": "",
"rel": [
"full",
"default"
],
"lastUpdated": "2022-12-09T00:28Z"
},
{
"href": "https://a.espncdn.com/i/teamlogos/ncaa/500-dark/2453.png",
"width": 500,
"height": 500,
"alt": "",
"rel": [
"full",
"dark"
],
"lastUpdated": "2022-12-09T00:26Z"
}
]
},
{
"team": "Jacksonville",
"link": "https://www.espn.com/womens-college-basketball/team/_/id/294/jacksonville-dolphins",
"id": "294",
"uid": "s:40~l:54~t:294",
"stats": [
{
"id": "0",
"name": "overall",
"abbreviation": "Season",
"displayName": "Team Season Record",
"shortDisplayName": "Season",
"description": "Overall Record",
"type": "total",
"summary": "12-13",
"displayValue": "12-13"
},
{
"name": "gamesBehind",
"displayName": "Games Back",
"shortDisplayName": "GB",
"description": "Games Back",
"abbreviation": "GB",
"type": "vsconf_gamesbehind",
"value": 7.0,
"displayValue": "7"
},
{
"id": "9",
"name": "vs. Conf.",
"abbreviation": "VS CONF",
"displayName": "CONF",
"shortDisplayName": "CONF",
"description": "Conference Record",
"type": "vsconf",
"summary": "6-7",
"displayValue": "6-7"
}
],
"logo": [
{
"href": "https://a.espncdn.com/i/teamlogos/ncaa/500/294.png",
"width": 500,
"height": 500,
"alt": "",
"rel": [
"full",
"default"
],
"lastUpdated": "2018-10-22T17:25Z"
},
{
"href": "https://a.espncdn.com/i/teamlogos/ncaa/500-dark/294.png",
"width": 500,
"height": 500,
"alt": "",
"rel": [
"full",
"dark"
],
"lastUpdated": "2018-10-22T17:26Z"
}
]
},
{
"team": "Bellarmine",
"link": "https://www.espn.com/womens-college-basketball/team/_/id/91/bellarmine-knights",
"id": "91",
"uid": "s:40~l:54~t:91",
"stats": [
{
"id": "0",
"name": "overall",
"abbreviation": "Season",
"displayName": "Team Season Record",
"shortDisplayName": "Season",
"description": "Overall Record",
"type": "total",
"summary": "14-11",
"displayValue": "14-11"
},
{
"name": "gamesBehind",
"displayName": "Games Back",
"shortDisplayName": "GB",
"description": "Games Back",
"abbreviation": "GB",
"type": "vsconf_gamesbehind",
"value": 7.5,
"displayValue": "7.5"
},
{
"id": "9",
"name": "vs. Conf.",
"abbreviation": "VS CONF",
"displayName": "CONF",
"shortDisplayName": "CONF",
"description": "Conference Record",
"type": "vsconf",
"summary": "5-7",
"displayValue": "5-7"
}
],
"logo": [
{
"href": "https://a.espncdn.com/i/teamlogos/ncaa/500/91.png",
"width": 500,
"height": 500,
"alt": "",
"rel": [
"full",
"default"
],
"lastUpdated": "2020-12-03T20:20Z"
},
{
"href": "https://a.espncdn.com/i/teamlogos/ncaa/500-dark/91.png",
"width": 500,
"height": 500,
"alt": "",
"rel": [
"full",
"dark"
],
"lastUpdated": "2020-12-03T20:22Z"
}
]
},
{
"team": "Austin Peay",
"link": "https://www.espn.com/womens-college-basketball/team/_/id/2046/austin-peay-governors",
"id": "2046",
"uid": "s:40~l:54~t:2046",
"stats": [
{
"id": "0",
"name": "overall",
"abbreviation": "Season",
"displayName": "Team Season Record",
"shortDisplayName": "Season",
"description": "Overall Record",
"type": "total",
"summary": "10-14",
"displayValue": "10-14"
},
{
"name": "gamesBehind",
"displayName": "Games Back",
"shortDisplayName": "GB",
"description": "Games Back",
"abbreviation": "GB",
"type": "vsconf_gamesbehind",
"value": 8.0,
"displayValue": "8"
},
{
"id": "9",
"name": "vs. Conf.",
"abbreviation": "VS CONF",
"displayName": "CONF",
"shortDisplayName": "CONF",
"description": "Conference Record",
"type": "vsconf",
"summary": "5-8",
"displayValue": "5-8"
}
],
"logo": [
{
"href": "https://a.espncdn.com/i/teamlogos/ncaa/500/2046.png",
"width": 500,
"height": 500,
"alt": "",
"rel": [
"full",
"default"
],
"lastUpdated": "2018-06-05T12:08Z"
},
{
"href": "https://a.espncdn.com/i/teamlogos/ncaa/500-dark/2046.png",
"width": 500,
"height": 500,
"alt": "",
"rel": [
"full",
"dark"
],
"lastUpdated": "2018-06-05T12:08Z"
}
]
},
{
"team": "West Georgia",
"link": "https://www.espn.com/womens-college-basketball/team/_/id/2698/west-georgia-wolves",
"id": "2698",
"uid": "s:40~l:54~t:2698",
"stats": [
{
"id": "0",
"name": "overall",
"abbreviation": "Season",
"displayName": "Team Season Record",
"shortDisplayName": "Season",
"description": "Overall Record",
"type": "total",
"summary": "10-14",
"displayValue": "10-14"
},
{
"name": "gamesBehind",
"displayName": "Games Back",
"shortDisplayName": "GB",
"description": "Games Back",
"abbreviation": "GB",
"type": "vsconf_gamesbehind",
"value": 9.0,
"displayValue": "9"
},
{
"id": "9",
"name": "vs. Conf.",
"abbreviation": "VS CONF",
"displayName": "CONF",
"shortDisplayName": "CONF",
"description": "Conference Record",
"type": "vsconf",
"summary": "4-9",
"displayValue": "4-9"
}
],
"logo": [
{
"href": "https://a.espncdn.com/i/teamlogos/ncaa/500/2698.png",
"width": 500,
"height": 500,
"alt": "",
"rel": [
"full",
"default"
],
"lastUpdated": "2023-01-12T14:37Z"
},
{
"href": "https://a.espncdn.com/i/teamlogos/ncaa/500-dark/2698.png",
"width": 500,
"height": 500,
"alt": "",
"rel": [
"full",
"dark"
],
"lastUpdated": "2023-01-12T14:37Z"
}
]
},
{
"team": "Queens University",
"link": "https://www.espn.com/womens-college-basketball/team/_/id/2511/queens-university-royals",
"id": "2511",
"uid": "s:40~l:54~t:2511",
"stats": [
{
"id": "0",
"name": "overall",
"abbreviation": "Season",
"displayName": "Team Season Record",
"shortDisplayName": "Season",
"description": "Overall Record",
"type": "total",
"summary": "8-16",
"displayValue": "8-16"
},
{
"name": "gamesBehind",
"displayName": "Games Back",
"shortDisplayName": "GB",
"description": "Games Back",
"abbreviation": "GB",
"type": "vsconf_gamesbehind",
"value": 11.0,
"displayValue": "11"
},
{
"id": "9",
"name": "vs. Conf.",
"abbreviation": "VS CONF",
"displayName": "CONF",
"shortDisplayName": "CONF",
"description": "Conference Record",
"type": "vsconf",
"summary": "2-11",
"displayValue": "2-11"
}
],
"logo": [
{
"href": "https://a.espncdn.com/i/teamlogos/ncaa/500/2511.png",
"width": 500,
"height": 500,
"alt": "",
"rel": [
"full",
"default"
],
"lastUpdated": "2022-07-22T17:10Z"
},
{
"href": "https://a.espncdn.com/i/teamlogos/ncaa/500-dark/2511.png",
"width": 500,
"height": 500,
"alt": "",
"rel": [
"full",
"dark"
],
"lastUpdated": "2022-07-22T17:11Z"
}
]
},
{
"team": "North Florida",
"link": "https://www.espn.com/womens-college-basketball/team/_/id/2454/north-florida-ospreys",
"id": "2454",
"uid": "s:40~l:54~t:2454",
"stats": [
{
"id": "0",
"name": "overall",
"abbreviation": "Season",
"displayName": "Team Season Record",
"shortDisplayName": "Season",
"description": "Overall Record",
"type": "total",
"summary": "4-22",
"displayValue": "4-22"
},
{
"name": "gamesBehind",
"displayName": "Games Back",
"shortDisplayName": "GB",
"description": "Games Back",
"abbreviation": "GB",
"type": "vsconf_gamesbehind",
"value": 13.0,
"displayValue": "13"
},
{
"id": "9",
"name": "vs. Conf.",
"abbreviation": "VS CONF",
"displayName": "CONF",
"shortDisplayName": "CONF",
"description": "Conference Record",
"type": "vsconf",
"summary": "0-13",
"displayValue": "0-13"
}
],
"logo": [
{
"href": "https://a.espncdn.com/i/teamlogos/ncaa/500/2454.png",
"width": 500,
"height": 500,
"alt": "",
"rel": [
"full",
"default"
],
"lastUpdated": "2021-09-01T21:40Z"
},
{
"href": "https://a.espncdn.com/i/teamlogos/ncaa/500-dark/2454.png",
"width": 500,
"height": 500,
"alt": "",
"rel": [
"full",
"dark"
],
"lastUpdated": "2021-09-01T21:41Z"
}
]
}
]
},
"header": "2024-25 ASUN Conference Standings",
"href": "https://www.espn.com/womens-college-basketball/standings/_/group/46"
}
]
},
"teamInfo": {},
"espnWP": {},
"season": [],
"timeouts": []
}